space_wrap.py
space_wrap-0.0.3.dist-info/LICENSE
space_wrap-0.0.3.dist-info/METADATA
space_wrap-0.0.3.dist-info/WHEEL
space_wrap-0.0.3.dist-info/top_level.txt
space_wrap-0.0.3.dist-info/RECORD
