Metadata-Version: 2.1
Name: space-wrap
Version: 0.0.3
Summary: Automated Spacy wrapper to turn plain text into Spacy doc objects
Home-page: https://github.com/eanthony1224
Download-URL: https://pypi.org/project/space_wrap/
Author: Evan Anthony
Author-email: anthonyevanm@gmail.com
License: MIT
Keywords: Spacy,tokenizer,NLP
License-File: LICENSE
Requires-Dist: pandas
Requires-Dist: spacy
